datasette_verify/__init__.py
datasette_verify-0.1.dist-info/METADATA
datasette_verify-0.1.dist-info/WHEEL
datasette_verify-0.1.dist-info/entry_points.txt
datasette_verify-0.1.dist-info/top_level.txt
datasette_verify-0.1.dist-info/RECORD
