Metadata-Version: 2.1
Name: datasette-verify
Version: 0.1
Summary: Verify that SQLite files can be opened using Datasette
Home-page: https://github.com/simonw/datasette-verify
Author: Simon Willison
License: Apache License, Version 2.0
Project-URL: Issues, https://github.com/simonw/datasette-verify/issues
Project-URL: CI, https://github.com/simonw/datasette-verify/actions
Project-URL: Changelog, https://github.com/simonw/datasette-verify/releases
Platform: UNKNOWN
Requires-Python: >=3.6
Requires-Dist: datasette (>=0.59a2)
Provides-Extra: test
Requires-Dist: pytest ; extra == 'test'
